taipy/__init__.py
taipy/rest/__init__.py
taipy/rest/_init.py
taipy/rest/app.py
taipy/rest/extensions.py
taipy/rest/rest.py
taipy/rest/version.json
taipy/rest/version.py
taipy/rest/api/__init__.py
taipy/rest/api/error_handler.py
taipy/rest/api/views.py
taipy/rest/api/exceptions/__init__.py
taipy/rest/api/exceptions/exceptions.py
taipy/rest/api/middlewares/__init__.py
taipy/rest/api/middlewares/_middleware.py
taipy/rest/api/resources/__init__.py
taipy/rest/api/resources/cycle.py
taipy/rest/api/resources/datanode.py
taipy/rest/api/resources/job.py
taipy/rest/api/resources/pipeline.py
taipy/rest/api/resources/scenario.py
taipy/rest/api/resources/task.py
taipy/rest/api/schemas/__init__.py
taipy/rest/api/schemas/cycle.py
taipy/rest/api/schemas/datanode.py
taipy/rest/api/schemas/job.py
taipy/rest/api/schemas/pipeline.py
taipy/rest/api/schemas/scenario.py
taipy/rest/api/schemas/task.py
taipy/rest/commons/__init__.py
taipy/rest/commons/apispec.py
taipy/rest/commons/encoder.py
taipy/rest/commons/pagination.py
taipy/rest/commons/to_from_model.py
taipy_rest-2.4.0.dist-info/LICENSE
taipy_rest-2.4.0.dist-info/METADATA
taipy_rest-2.4.0.dist-info/WHEEL
taipy_rest-2.4.0.dist-info/top_level.txt
taipy_rest-2.4.0.dist-info/RECORD
