Metadata-Version: 2.1
Name: taipy-rest
Version: 2.4.0
Summary: Library to expose taipy-core REST APIs.
Author: Avaiga
Author-email: dev@taipy.io
License: Apache License 2.0
Keywords: taipy-rest
Classifier: Intended Audience :: Developers
Classifier: License :: OSI Approved :: Apache Software License
Classifier: Natural Language :: English
Classifier: Programming Language :: Python :: 3
Classifier: Programming Language :: Python :: 3.8
Classifier: Programming Language :: Python :: 3.9
Classifier: Programming Language :: Python :: 3.10
Classifier: Programming Language :: Python :: 3.11
Requires-Python: >=3.8
License-File: LICENSE
